demotivate.py
demotivate-1.0.0.dist-info/LICENSE
demotivate-1.0.0.dist-info/METADATA
demotivate-1.0.0.dist-info/WHEEL
demotivate-1.0.0.dist-info/entry_points.txt
demotivate-1.0.0.dist-info/top_level.txt
demotivate-1.0.0.dist-info/RECORD
