Metadata-Version: 2.1
Name: demotivate
Version: 1.0.0
Summary: A simple script to print random demotivations.
Author-email: Michael de Villiers <michael@devilears.co.za>
Maintainer-email: Michael de Villiers <michael@devilears.co.za>
License: WTFPLv2
Project-URL: Source Code, https://github.com/COUR4G3/demotivate/
Project-URL: Issue Tracker, https://github.com/COUR4G3/demotivate/
Classifier: Development Status :: 5 - Production/Stable
Classifier: Environment :: Console
Classifier: Intended Audience :: End Users/Desktop
Classifier: Operating System :: OS Independent
Classifier: Programming Language :: Python
Classifier: Topic :: Utilities
Requires-Python: >=3.8
License-File: LICENSE
Requires-Dist: click ~=8.1.7
Provides-Extra: dev
Requires-Dist: bandit ; extra == 'dev'
Requires-Dist: black ; extra == 'dev'
Requires-Dist: flake8 ; extra == 'dev'
Requires-Dist: isort ; extra == 'dev'
Requires-Dist: pre-commit ~=2.21.0 ; extra == 'dev'
Requires-Dist: pydocstyle ; extra == 'dev'
